libfluora/__init__.py
libfluora/device_info.py
libfluora/fragmented_state_manager.py
libfluora/pixelair_client.py
libfluora/pixelair_device.py
libfluora/pixelair_device_fixed.py
libfluora/pixelair_generated.py
libfluora/pixelair_state.py
libfluora-0.1.5.dist-info/LICENSE
libfluora-0.1.5.dist-info/METADATA
libfluora-0.1.5.dist-info/WHEEL
libfluora-0.1.5.dist-info/RECORD
