Metadata-Version: 2.1
Name: libfluora
Version: 0.1.5
Summary: 
Author: Aiden Vigue
Author-email: aiden@vigue.me
Requires-Python: >=3.12,<4.0
Classifier: Programming Language :: Python :: 3
Classifier: Programming Language :: Python :: 3.12
Requires-Dist: flatbuffers (>=25.2.10,<26.0.0)
Requires-Dist: netifaces (>=0.11.0,<0.12.0)
Requires-Dist: python-osc (>=1.8.3,<2.0.0)
